lapels
