Metadata-Version: 1.0
Name: lapels
Version: 1.0.1
Summary: Lapels - A remapper and annotator of in silico (pseudo) genome alignments
Home-page: http://code.google.com/p/lapels/
Author: Shunping Huang
Author-email: mark.sphuang@gmail.com
License: The MIT License
Keywords: lapels remap position bam mod
Platform: Linux
